MANIFEST.in
README.md
setup.cfg
setup.py
wagtail_tinypng/__init__.py
wagtail_tinypng/apps.py
wagtail_tinypng/models.py
wagtail_tinypng/tests.py
wagtail_tinypng/utils.py
wagtail_tinypng/views.py
wagtail_tinypng/wagtail_hooks.py
wagtail_tinypng/management/.DS_Store
wagtail_tinypng/management/commands/sync_tinypng_images.py
wagtail_tinypng/migrations/0001_initial.py
wagtail_tinypng/migrations/__init__.py
wagtail_tinypng/templates/wagtailimages/images/edit.html
wagtail_tinypng/templatetags/wagtail_tinypng.py
wagtailtinypng.egg-info/PKG-INFO
wagtailtinypng.egg-info/SOURCES.txt
wagtailtinypng.egg-info/dependency_links.txt
wagtailtinypng.egg-info/requires.txt
wagtailtinypng.egg-info/top_level.txt