Metadata-Version: 1.1
Name: wagtailtinypng
Version: 0.0.3
Summary: Allow lossless .jpeg, .jpg, and .png compression through the Wagtail admin interface using tinypng.com.
Home-page: https://github.com/KalobTaulien/wagtail-tinypng
Author: Kalob Taulien
Author-email: kalob@kalob.io
License: MIT
Keywords: development
Platform: UNKNOWN
Classifier: Development Status :: 4 - Beta
Classifier: Operating System :: OS Independent
Classifier: Environment :: Web Environment
Classifier: Framework :: Django
Classifier: Framework :: Django :: 2.0
Classifier: Framework :: Django :: 2.1
Classifier: Framework :: Django :: 2.2
Classifier: Framework :: Wagtail
Classifier: Framework :: Wagtail :: 2
Classifier: Programming Language :: Python
Classifier: Programming Language :: Python :: 3.5
Classifier: Programming Language :: Python :: 3.6
Classifier: Programming Language :: Python :: 3.7
Classifier: Intended Audience :: Developers
Classifier: Topic :: Internet :: WWW/HTTP
Classifier: Topic :: Internet :: WWW/HTTP :: Dynamic Content
